<?xml version="1.0" encoding="UTF-8" standalone="no"?>
<Pais Informacion="Informacion generica" Nombre="Argentina">
   <Edificios>
      <Edificio Nombre="biblioteca" Pista="Nunca he visto a la persona que dices"/>
      <Edificio Nombre="puerto" Pista="No he visto a nadie como dices"/>
      <Edificio Nombre="fiuba" Pista="No he visto a nadie como dices"/>
   </Edificios>
   <Coordenadas>
      <Coordenadas Latitud="1.0" Longitud="1.0"/>
   </Coordenadas>
   <Pais Informacion="Informacion generica" Nombre="Brasil">
      <Edificios>
         <Edificio Nombre="biblioteca" Pista="Nunca he visto a la persona que dices"/>
         <Edificio Nombre="puerto" Pista="No he visto a nadie como dices"/>
         <Edificio Nombre="fiuba" Pista="No he visto a nadie como dices"/>
      </Edificios>
      <Coordenadas>
         <Coordenadas Latitud="1.0" Longitud="3.0"/>
      </Coordenadas>
   </Pais>
</Pais>
